__init__.py
nenet.py
nenet-0.0.1.dist-info/LICENCE
nenet-0.0.1.dist-info/METADATA
nenet-0.0.1.dist-info/WHEEL
nenet-0.0.1.dist-info/top_level.txt
nenet-0.0.1.dist-info/RECORD
