Metadata-Version: 2.1
Name: nenet
Version: 0.0.1
Summary: Nenet is a python package for training and test neural networks models on tabular data
Author-email: Juan Pablo Saavedra Guerin <juan.saavedra.g@mail.pucv.cl>
Project-URL: Homepage, https://github.com/jpsaavedraguerin/nenet
Classifier: Programming Language :: Python :: 3
Classifier: License :: OSI Approved :: MIT License
Classifier: Operating System :: OS Independent
Requires-Python: >=3.10.6
License-File: LICENCE
